cli/__init__.py
honeycomb/__init__.py
honeycomb/models.py
wildflower_honeycomb_sdk-0.7.3.dist-info/LICENSE
wildflower_honeycomb_sdk-0.7.3.dist-info/METADATA
wildflower_honeycomb_sdk-0.7.3.dist-info/WHEEL
wildflower_honeycomb_sdk-0.7.3.dist-info/entry_points.txt
wildflower_honeycomb_sdk-0.7.3.dist-info/top_level.txt
wildflower_honeycomb_sdk-0.7.3.dist-info/RECORD
